{"description":"Get ready for a thrilling adventure as mysterious dino eggs are about to hatch! \nThese eggs have been discovered in a remote location and are believed to hold rare and exotic dinosaur species. \nAs the eggs start to crack, we'll witness the emergence of these incredible creatures, and the world will never be the same again!","discord_link":"https://discord.gg/AnvgByy786","inscription_icon":"578ac5c4eebf5b6f5c93c869ae840cd8bafc4dbfa01c9002ca36b213ac2e6662i0","name":"Bitcoin Dinos Eggs","slug":"bitcoin-dinos-eggs","twitter_link":"https://twitter.com/BTC_Dinos","website_link":"","inscription_min":466014,"inscription_max":717517,"category_attributes":["Orange Btc","1/1","Black&Orange","Black","1/1","Red","Light Blue","1/1","Black&LightBlue","Black","1/1","White","Black","1/1","Pink&Beige","Beige","1/1","LightBlue&White","Dark Grey","1/1","Black&Green","Light Red","1/1","Black&LightRed","Light Purple","1/1","White&Pink&Purple","White","1/1","Gameboy","Light Pink","Fushia&Blue","Light Grey","2Green","Light Blue","White&Orange","Marine Blue","White&Orange","Orange","White&Orange","Fushia","Red&LightBlue","Bright Red","White&Orange","Purple","Light Green","Bright Red","Half&Half","Matrix","White&Orange","Orange","Ying/Yang","Marine Blue","Orange&Green","Marine Blue","Red&LightBlue","Bright Red ","Black&Orange","Light Purple","BlueSky&Pink","Marine Blue","Half&Half","Purple","Black&Orange","Pink","Light Green","Yellow","Ying/Yang","Purple","Mint","Orange","2Green","Light Blue","Light Green","Yellow","White&Orange","Matrix","Black&Orange","Fushia","White&Orange","Fushia","Black&Orange","Green","2Green","Pink","Orange&Green","Light Green","Mint","Light Purple","Fushia&Blue","Marine Blue","Light Green","Matrix","Ying/Yang","Yellow","Half&Half","Orange","Black&Orange","Pink","BlueSky&Pink","Orange","Mint","Light Purple","Mint","Light Green","Orange&Green","Light Green","2Green","Yellow","BlueSky&Pink"]}